spsshrunner/__init__.py
spsshrunner/sshrunner.py
spsshrunner-0.0.3.dist-info/METADATA
spsshrunner-0.0.3.dist-info/WHEEL
spsshrunner-0.0.3.dist-info/top_level.txt
spsshrunner-0.0.3.dist-info/RECORD
