Metadata-Version: 2.1
Name: spsshrunner
Version: 0.0.3
Summary: Facilitate SSH expect flows
Home-page: https://github.com/steviepy/spsshrunner
Author: Stevie Py
Author-email: st3v13py@gmail.com
License: UNKNOWN
Platform: UNKNOWN
Classifier: Programming Language :: Python :: 3
Classifier: License :: OSI Approved :: MIT License
Classifier: Operating System :: OS Independent
